bitpeer/__init__.py
bitpeer/clients.py
bitpeer/exceptions.py
bitpeer/fields.py
bitpeer/keys.py
bitpeer/log.py
bitpeer/networks.py
bitpeer/node.py
bitpeer/serializers.py
bitpeer/util.py
bitpeer/storage/__init__.py
bitpeer/storage/mem.py
bitpeer/storage/shelve.py
bitpeer/storage/storage.py
bitpeer.py-0.4.7.5.dist-info/DESCRIPTION.rst
bitpeer.py-0.4.7.5.dist-info/METADATA
bitpeer.py-0.4.7.5.dist-info/RECORD
bitpeer.py-0.4.7.5.dist-info/WHEEL
bitpeer.py-0.4.7.5.dist-info/metadata.json
bitpeer.py-0.4.7.5.dist-info/top_level.txt
bitpeer.py-0.4.7.5.dist-info/zip-safe
