Metadata-Version: 2.0
Name: bitpeer.py
Version: 0.4.7.5
Summary: A pure Python3 bitcoin protocol implementation.
Home-page: https://github.com/dakk/bitpeer.py
Author: Davide Gessa, Christian S. Perone
Author-email: gessadavide@gmail.com, christian.perone@gmail.com
License: BSD License
Keywords: bitcoin,protocol,blockchain,litecoin,testnet,bitpeer,peer
Platform: Any
Classifier: Development Status :: 4 - Beta
Classifier: Operating System :: OS Independent
Classifier: Programming Language :: Python
Classifier: Topic :: Software Development :: Libraries :: Python Modules
Requires-Dist: ecdsa (>=0.10)
Requires-Dist: pycoin (==0.62)
